buildingspy/CHANGES.txt
buildingspy/README.rst
buildingspy/VERSION
buildingspy/__init__.py
buildingspy/license.txt
buildingspy/development/__init__.py
buildingspy/development/dymola_run.template
buildingspy/development/error_dictionary.py
buildingspy/development/error_dictionary_dymola.py
buildingspy/development/error_dictionary_openmodelica.py
buildingspy/development/error_dictionary_optimica.py
buildingspy/development/merger.py
buildingspy/development/openmodelica_run.template
buildingspy/development/optimica_run.template
buildingspy/development/refactor.py
buildingspy/development/regressiontest.py
buildingspy/development/run_all.template
buildingspy/development/simulationCompare.py
buildingspy/development/validator.py
buildingspy/examples/__init__.py
buildingspy/examples/dymola/PlotDemo.mat
buildingspy/examples/dymola/TwoRoomsWithStorage.mat
buildingspy/examples/dymola/__init__.py
buildingspy/examples/dymola/plot.pdf
buildingspy/examples/dymola/plot.png
buildingspy/examples/dymola/plotResult.py
buildingspy/examples/dymola/runSimulation.py
buildingspy/examples/dymola/case1/FlatPlateWithTank.mat
buildingspy/examples/dymola/case2/FlatPlateWithTank.mat
buildingspy/fmi/__init__.py
buildingspy/io/__init__.py
buildingspy/io/outputfile.py
buildingspy/io/postprocess.py
buildingspy/io/reporter.py
buildingspy/simulate/Dymola.py
buildingspy/simulate/OpenModelica.py
buildingspy/simulate/Optimica.py
buildingspy/simulate/OutputGrabber.py
buildingspy/simulate/__init__.py
buildingspy/simulate/base_simulator.py
buildingspy/templates/datatable.html
buildingspy/templates/plot.html
buildingspy/templates/regressiontest_conf.py
buildingspy/tests/MyModelicaLibrary/MyModel.mo
buildingspy/tests/MyModelicaLibrary/MyModelTimeOut.mo
buildingspy/tests/MyModelicaLibrary/MyStep.mo
buildingspy/tests/MyModelicaLibrary/package.mo
buildingspy/tests/MyModelicaLibrary/Examples/BooleanParameters.mo
buildingspy/tests/MyModelicaLibrary/Examples/Constants.mo
buildingspy-5.2.0.dist-info/METADATA
buildingspy-5.2.0.dist-info/WHEEL
buildingspy-5.2.0.dist-info/top_level.txt
buildingspy-5.2.0.dist-info/RECORD
